.DS_Store
GoogleNewsScraper/.DS_Store
GoogleNewsScraper/__init__.py
GoogleNewsScraper/chromedriver/.DS_Store
GoogleNewsScraper/chromedriver/chromedriver
GoogleNewsScraper-1.0.1.dist-info/LICENSE
GoogleNewsScraper-1.0.1.dist-info/METADATA
GoogleNewsScraper-1.0.1.dist-info/WHEEL
GoogleNewsScraper-1.0.1.dist-info/top_level.txt
GoogleNewsScraper-1.0.1.dist-info/RECORD
