Metadata-Version: 2.1
Name: GoogleNewsScraper
Version: 1.0.1
Summary: Scrapes Google News article data
Home-page: https://github.com/GeminidSystems/google_news_scraper
Author: Geminid Systems
Author-email: dev@geminidsystems.com
License: UNKNOWN
Platform: UNKNOWN
Classifier: Programming Language :: Python :: 3.6
Classifier: License :: OSI Approved :: MIT License
Classifier: Operating System :: OS Independent
License-File: LICENSE
Requires-Dist: selenium
